Workbook

Sheet Dashboard
O1: =O4/O5 -> 0.55
B2: Essence Alpha Assessment
B3: Project progress & performance — kernel + practices, measured by alpha state · assessed at the Solution level (see the Levels of Scale tab) | O3: 14
O4: =Opportunity!M1+Stakeholders!M1+'Business Scenario'!M1+'Service Blueprint'!M1+Requirements!M1+System!M1+'Architectural Drivers'!M1+Architecture!M1+'Architecture Decisions'!M1+'Paved Road'!M1+Work!M1+Team!M1+'Way of Working'!M1+Governance!M1 -> 121
B5: OVERALL COMPLETION | D5: ALPHAS COMPLETE | F5: CHECKLIST ITEMS | O5: =Opportunity!M2+Stakeholders!M2+'Business Scenario'!M2+'Service Blueprint'!M2+Requirements!M2+System!M2+'Architectural Drivers'!M2+Architecture!M2+'Architecture Decisions'!M2+'Paved Road'!M2+Work!M2+Team!M2+'Way of Working'!M2+Governance!M2 -> 220
B6: =O1 -> 0.55 | D6: =COUNTIF(H9:H25,"✔ Complete")&" / "&O3 -> 1 / 14 | F6: =O4&" / "&O5 -> 121 / 220
B8: ALPHA | C8: OWNER | D8: LEVEL | E8: CURRENT STATE | F8: PROGRESS | G8: TARGET STATE | H8: STATUS
B9: CUSTOMER
B10: Opportunity | C10: Kernel | D10: Solution | E10: =Opportunity!B5 -> Value Established | F10: =Opportunity!C5 -> 0.65217391 | G10: Benefit Accrued | H10: =IF(F10>=1,"✔ Complete",IF(F10>0,"● In progress","○ Not started")) -> ● In progress
B11: Stakeholders | C11: Kernel | D11: Solution | E11: =Stakeholders!B5 -> In Agreement | F11: =Stakeholders!C5 -> 0.78947368 | G11: Satisfied in Use | H11: =IF(F11>=1,"✔ Complete",IF(F11>0,"● In progress","○ Not started")) -> ● In progress
B12: Business Scenario | C12: Business Scenarios | D12: Enterprise | E12: ='Business Scenario'!B5 -> Released | F12: ='Business Scenario'!C5 -> 1 | G12: Released | H12: =IF(F12>=1,"✔ Complete",IF(F12>0,"● In progress","○ Not started")) -> ✔ Complete
B13: Service Blueprint | C13: Service Blueprint | D13: Solution | E13: ='Service Blueprint'!B5 -> Blueprinted | F13: ='Service Blueprint'!C5 -> 0.7 | G13: In Operation | H13: =IF(F13>=1,"✔ Complete",IF(F13>0,"● In progress","○ Not started")) -> ● In progress
B14: SOLUTION
B15: Requirements | C15: Kernel | D15: Solution | E15: =Requirements!B5 -> Bounded | F15: =Requirements!C5 -> 0.56666667 | G15: Fulfilled | H15: =IF(F15>=1,"✔ Complete",IF(F15>0,"● In progress","○ Not started")) -> ● In progress
B16: System | C16: Kernel | D16: Solution | E16: =System!B5 -> Not started | F16: =System!C5 -> 0 | G16: Operational | H16: =IF(F16>=1,"✔ Complete",IF(F16>0,"● In progress","○ Not started")) -> ○ Not started
B17: Architectural Drivers | C17: MVA | D17: Solution | E17: ='Architectural Drivers'!B5 -> Quantified | F17: ='Architectural Drivers'!C5 -> 0.7 | G17: Sustained | H17: =IF(F17>=1,"✔ Complete",IF(F17>0,"● In progress","○ Not started")) -> ● In progress
B18: Architecture | C18: MVA | D18: Solution | E18: =Architecture!B5 -> Demonstrated | F18: =Architecture!C5 -> 0.63636364 | G18: Established | H18: =IF(F18>=1,"✔ Complete",IF(F18>0,"● In progress","○ Not started")) -> ● In progress
B19: Architecture Decisions | C19: MVA | D19: Solution | E19: ='Architecture Decisions'!B5 -> Communicated | F19: ='Architecture Decisions'!C5 -> 0.8 | G19: Validated | H19: =IF(F19>=1,"✔ Complete",IF(F19>0,"● In progress","○ Not started")) -> ● In progress
B20: Paved Road | C20: MVA | D20: Enterprise | E20: ='Paved Road'!B5 -> Established | F20: ='Paved Road'!C5 -> 0.5 | G20: Pervasive | H20: =IF(F20>=1,"✔ Complete",IF(F20>0,"● In progress","○ Not started")) -> ● In progress
B21: ENDEAVOR
B22: Work | C22: Kernel | D22: Solution | E22: =Work!B5 -> Prepared | F22: =Work!C5 -> 0.57894737 | G22: Closed | H22: =IF(F22>=1,"✔ Complete",IF(F22>0,"● In progress","○ Not started")) -> ● In progress
B23: Team | C23: Kernel | D23: Solution | E23: =Team!B5 -> Formed | F23: =Team!C5 -> 0.64705882 | G23: Performing | H23: =IF(F23>=1,"✔ Complete",IF(F23>0,"● In progress","○ Not started")) -> ● In progress
B24: Way of Working | C24: Kernel | D24: Solution | E24: ='Way of Working'!B5 -> Foundation Established | F24: ='Way of Working'!C5 -> 0.41176471 | G24: Working Well | H24: =IF(F24>=1,"✔ Complete",IF(F24>0,"● In progress","○ Not started")) -> ● In progress
B25: Governance | C25: MVG | D25: Spans | E25: =Governance!B5 -> Guiding | F25: =Governance!C5 -> 0.7 | G25: Effective | H25: =IF(F25>=1,"✔ Complete",IF(F25>0,"● In progress","○ Not started")) -> ● In progress
B27: Tip: open any alpha tab and tick the ✔ column (dropdown) per checklist item. Current state, progress and this dashboard update automatically. • Sample data shown — clear the ✔ cells to start your own assessment.
B28: Status: ✔ Complete ● In progress ○ Not started Level: Enterprise (inherited) · Solution (owned here) · Spans
B29: → See the 'Levels of Scale' tab for how the levels work

Sheet Levels of Scale
B2: Levels of Scale — naming the System
B3: The System alpha is the system of interest — and it is fractal. Choose the level before you assess.
B5: An enterprise is a system of systems; a solution is a sub-system of the enterprise; a configured product is a sub-system of the solution. The same kernel and practices instantiate at any level — and what is a System at one level is a sub-system at the level above. The boundary you draw decides what every alpha actually measures.
B8: ENTERPRISE — System = the enterprise Enterprise architecture, the paved road, drivers and standing governance are owned here. Each solution rolls up into the enterprise.
C10: SOLUTION / PROJECT — System = the solution Inherits the enterprise paved road, drivers and governance as context; owns the architecture and decisions for this solution.
D12: COMPONENT — System = a configured product A sub-system of the solution, tracked in its own right when it warrants it.
B15: The same kernel + practices run at each level; a System at one level is a sub-system at the one above.
B17: WHICH PRACTICE RUNS WHERE
B18: ENTERPRISE → | C18: Business Scenarios (set the drivers) · enterprise MVA · MVG (guardrails + paved road) — handed down as context
B19: SOLUTION → | C19: Service Blueprint (design the service) · MVA (architect within the guardrails) — feeds evidence & new drivers back up
B21: This workbook assesses the SOLUTION level. Alphas owned here are tagged Solution; the Paved Road and the (enterprise) Business Scenario are inherited from the Enterprise; Governance spans levels. The level tag appears on each alpha tab (top-right) and in the dashboard.

Sheet Opportunity
B1: ← Dashboard | M1: =SUM(H7:H12) -> 15
B2: Opportunity | E2: SOLUTION | M2: =SUM(I7:I12) -> 23
B3: The circumstances that make a new or changed system worthwhile. | M3: =SUM(K7:K12) -> 3
B4: CURRENT STATE | C4: PROGRESS | D4: STATES ACHIEVED | E4: OWNER · AREA | M4: =SUM(J7:J12) -> 3
B5: =IF(M3=0,"Not started",INDEX(G7:G12,M3)) -> Value Established | C5: =IF(M2=0,0,M1/M2) -> 0.65217391 | D5: =M4&" / "&6 -> 3 / 6 | E5: Kernel · Customer
B6: STATE | C6: ✔ | D6: CHECKLIST ITEM | E6: STATE STATUS
B7: 1. Identified | C7: ✔ | D7: An idea for improving the way of working, increasing market share or applying a new system has been identified. | E7: =COUNTIF(C7:C9,"✔")&" / 3" -> 3 / 3 | G7: Identified | H7: =COUNTIF(C7:C9,"✔") -> 3 | I7: 3 | J7: =IF(H7=I7,1,0) -> 1 | K7: =J7 -> 1
C8: ✔ | D8: At least one stakeholder wishes to invest in understanding the opportunity and its value. | G8: Solution Needed | H8: =COUNTIF(C10:C14,"✔") -> 5 | I8: 5 | J8: =IF(H8=I8,1,0) -> 1 | K8: =J8*K7 -> 1
C9: ✔ | D9: The other stakeholders who share the opportunity have been identified. | G9: Value Established | H9: =COUNTIF(C15:C19,"✔") -> 5 | I9: 5 | J9: =IF(H9=I9,1,0) -> 1 | K9: =J9*K8 -> 1
B10: 2. Solution Needed | C10: ✔ | D10: The stakeholders in the opportunity and the proposed solution have been identified. | E10: =COUNTIF(C10:C14,"✔")&" / 5" -> 5 / 5 | G10: Viable | H10: =COUNTIF(C20:C24,"✔") -> 2 | I10: 5 | J10: =IF(H10=I10,1,0) -> 0 | K10: =J10*K9 -> 0
C11: ✔ | D11: The stakeholder needs that generate the opportunity have been established. | G11: Addressed | H11: =COUNTIF(C25:C27,"✔") -> 0 | I11: 3 | J11: =IF(H11=I11,1,0) -> 0 | K11: =J11*K10 -> 0
C12: ✔ | D12: Any underlying problems and their root causes have been identified. | G12: Benefit Accrued | H12: =COUNTIF(C28:C29,"✔") -> 0 | I12: 2 | J12: =IF(H12=I12,1,0) -> 0 | K12: =J12*K11 -> 0
C13: ✔ | D13: It has been confirmed that a system-based solution is needed.
C14: ✔ | D14: At least one solution has been proposed.
B15: 3. Value Established | C15: ✔ | D15: The value of addressing the opportunity has been quantified. | E15: =COUNTIF(C15:C19,"✔")&" / 5" -> 5 / 5
C16: ✔ | D16: The impact of the solution on the stakeholders is understood.
C17: ✔ | D17: The value the system offers to those who fund and use it is understood.
C18: ✔ | D18: The success criteria for the deployment are clear.
C19: ✔ | D19: The desired outcomes are clear and quantified.
B20: 4. Viable | C20: ✔ | D20: A solution has been outlined. | E20: =COUNTIF(C20:C24,"✔")&" / 5" -> 2 / 5
C21: ✔ | D21: The solution can be developed and deployed within the constraints.
D22: The risks associated with the solution are acceptable and manageable.
D23: The ball-park costs are less than the anticipated value of the opportunity.
D24: It is clear that pursuing the opportunity is viable.
B25: 5. Addressed | D25: A usable system that demonstrably addresses the opportunity is available. | E25: =COUNTIF(C25:C27,"✔")&" / 3" -> 0 / 3
D26: The stakeholders agree the available solution is worth deploying.
D27: The stakeholders are satisfied the solution addresses the opportunity.
B28: 6. Benefit Accrued | D28: The solution has started to accrue benefits for the stakeholders. | E28: =COUNTIF(C28:C29,"✔")&" / 2" -> 0 / 2
D29: The return-on-investment is at least as good as anticipated.

Sheet Stakeholders
B1: ← Dashboard | M1: =SUM(H7:H12) -> 15
B2: Stakeholders | E2: SOLUTION | M2: =SUM(I7:I12) -> 19
B3: The people and groups that affect or are affected by the system. | M3: =SUM(K7:K12) -> 4
B4: CURRENT STATE | C4: PROGRESS | D4: STATES ACHIEVED | E4: OWNER · AREA | M4: =SUM(J7:J12) -> 4
B5: =IF(M3=0,"Not started",INDEX(G7:G12,M3)) -> In Agreement | C5: =IF(M2=0,0,M1/M2) -> 0.78947368 | D5: =M4&" / "&6 -> 4 / 6 | E5: Kernel · Customer
B6: STATE | C6: ✔ | D6: CHECKLIST ITEM | E6: STATE STATUS
B7: 1. Recognized | C7: ✔ | D7: The stakeholder groups are identified. | E7: =COUNTIF(C7:C9,"✔")&" / 3" -> 3 / 3 | G7: Recognized | H7: =COUNTIF(C7:C9,"✔") -> 3 | I7: 3 | J7: =IF(H7=I7,1,0) -> 1 | K7: =J7 -> 1
C8: ✔ | D8: The key stakeholder groups are represented. | G8: Represented | H8: =COUNTIF(C10:C13,"✔") -> 4 | I8: 4 | J8: =IF(H8=I8,1,0) -> 1 | K8: =J8*K7 -> 1
C9: ✔ | D9: The responsibilities of the stakeholder representatives are defined. | G9: Involved | H9: =COUNTIF(C14:C16,"✔") -> 3 | I9: 3 | J9: =IF(H9=I9,1,0) -> 1 | K9: =J9*K8 -> 1
B10: 2. Represented | C10: ✔ | D10: The representatives have agreed their responsibilities. | E10: =COUNTIF(C10:C13,"✔")&" / 4" -> 4 / 4 | G10: In Agreement | H10: =COUNTIF(C17:C21,"✔") -> 5 | I10: 5 | J10: =IF(H10=I10,1,0) -> 1 | K10: =J10*K9 -> 1
C11: ✔ | D11: The representatives are authorized to carry out their responsibilities. | G11: Satisfied for Deployment | H11: =COUNTIF(C22:C23,"✔") -> 0 | I11: 2 | J11: =IF(H11=I11,1,0) -> 0 | K11: =J11*K10 -> 0
C12: ✔ | D12: The collaboration approach among representatives is agreed. | G12: Satisfied in Use | H12: =COUNTIF(C24:C25,"✔") -> 0 | I12: 2 | J12: =IF(H12=I12,1,0) -> 0 | K12: =J12*K11 -> 0
C13: ✔ | D13: The team's way of working is supported and respected by the stakeholders.
B14: 3. Involved | C14: ✔ | D14: The representatives assist the team in line with their responsibilities. | E14: =COUNTIF(C14:C16,"✔")&" / 3" -> 3 / 3
C15: ✔ | D15: The representatives provide feedback and take decisions in a timely manner.
C16: ✔ | D16: Changes are promptly communicated to the team and stakeholders.
B17: 4. In Agreement | C17: ✔ | D17: The minimal expectations of the stakeholder groups are agreed. | E17: =COUNTIF(C17:C21,"✔")&" / 5" -> 5 / 5
C18: ✔ | D18: The representatives are happy with their involvement.
C19: ✔ | D19: The representatives' input is valued by the team.
C20: ✔ | D20: The team's input is valued by the representatives.
C21: ✔ | D21: Priorities are clear and perspectives balanced.
B22: 5. Satisfied for Deployment | D22: The representatives provide feedback on the system from their group's perspective. | E22: =COUNTIF(C22:C23,"✔")&" / 2" -> 0 / 2
D23: The representatives confirm the system is ready for deployment.
B24: 6. Satisfied in Use | D24: The stakeholders are using the system and providing feedback. | E24: =COUNTIF(C24:C25,"✔")&" / 2" -> 0 / 2
D25: The stakeholders confirm the system meets their expectations.

Sheet Requirements
B1: ← Dashboard | M1: =SUM(H7:H12) -> 17
B2: Requirements | E2: SOLUTION | M2: =SUM(I7:I12) -> 30
B3: What the system must do to address the opportunity and satisfy the stakeholders. | M3: =SUM(K7:K12) -> 2
B4: CURRENT STATE | C4: PROGRESS | D4: STATES ACHIEVED | E4: OWNER · AREA | M4: =SUM(J7:J12) -> 2
B5: =IF(M3=0,"Not started",INDEX(G7:G12,M3)) -> Bounded | C5: =IF(M2=0,0,M1/M2) -> 0.56666667 | D5: =M4&" / "&6 -> 2 / 6 | E5: Kernel · Solution
B6: STATE | C6: ✔ | D6: CHECKLIST ITEM | E6: STATE STATUS
B7: 1. Conceived | C7: ✔ | D7: The initial stakeholders agree a system is to be produced. | E7: =COUNTIF(C7:C10,"✔")&" / 4" -> 4 / 4 | G7: Conceived | H7: =COUNTIF(C7:C10,"✔") -> 4 | I7: 4 | J7: =IF(H7=I7,1,0) -> 1 | K7: =J7 -> 1
C8: ✔ | D8: The stakeholders that will use the system are identified. | G8: Bounded | H8: =COUNTIF(C11:C19,"✔") -> 9 | I8: 9 | J8: =IF(H8=I8,1,0) -> 1 | K8: =J8*K7 -> 1
C9: ✔ | D9: The stakeholders that will fund the initial work are identified. | G9: Coherent | H9: =COUNTIF(C20:C26,"✔") -> 4 | I9: 7 | J9: =IF(H9=I9,1,0) -> 0 | K9: =J9*K8 -> 0
C10: ✔ | D10: There is a clear opportunity for the system to address. | G10: Acceptable | H10: =COUNTIF(C27:C30,"✔") -> 0 | I10: 4 | J10: =IF(H10=I10,1,0) -> 0 | K10: =J10*K9 -> 0
B11: 2. Bounded | C11: ✔ | D11: The stakeholders involved in developing the system are identified. | E11: =COUNTIF(C11:C19,"✔")&" / 9" -> 9 / 9 | G11: Addressed | H11: =COUNTIF(C31:C33,"✔") -> 0 | I11: 3 | J11: =IF(H11=I11,1,0) -> 0 | K11: =J11*K10 -> 0
C12: ✔ | D12: The stakeholders agree on the purpose of the system. | G12: Fulfilled | H12: =COUNTIF(C34:C36,"✔") -> 0 | I12: 3 | J12: =IF(H12=I12,1,0) -> 0 | K12: =J12*K11 -> 0
C13: ✔ | D13: It is clear what success is for the system.
C14: ✔ | D14: There is a shared understanding of the extent of the solution.
C15: ✔ | D15: The way the requirements will be described is agreed.
C16: ✔ | D16: The mechanisms for managing requirements are in place.
C17: ✔ | D17: The prioritization scheme is clear.
C18: ✔ | D18: Constraints are identified and considered.
C19: ✔ | D19: Assumptions are clearly stated.
B20: 3. Coherent | C20: ✔ | D20: The requirements are captured and shared with team and stakeholders. | E20: =COUNTIF(C20:C26,"✔")&" / 7" -> 4 / 7
C21: ✔ | D21: The origin and rationale of the requirements are clear.
C22: ✔ | D22: Conflicting requirements are identified and addressed.
C23: ✔ | D23: The requirements convey the essential characteristics of the system.
D24: The most important usage scenarios can be explained.
D25: The priority of the requirements is clear.
D26: The team understands what must be delivered and agrees to deliver it.
B27: 4. Acceptable | D27: The stakeholders accept the requirements describe an acceptable solution. | E27: =COUNTIF(C27:C30,"✔")&" / 4" -> 0 / 4
D28: The rate of change to agreed requirements is low and under control.
D29: The value of implementing the requirements is clear.
D30: The requirements are testable.
B31: 5. Addressed | D31: Enough requirements are addressed for the system to be acceptable. | E31: =COUNTIF(C31:C33,"✔")&" / 3" -> 0 / 3
D32: The implemented requirement items provide clear value.
D33: The system is accepted by the stakeholders as worth making operational.
B34: 6. Fulfilled | D34: The stakeholders accept the requirements capture what they need. | E34: =COUNTIF(C34:C36,"✔")&" / 3" -> 0 / 3
D35: No outstanding requirement items prevent acceptance.
D36: The system fully satisfies the requirements.

Sheet System
B1: ← Dashboard | M1: =SUM(H7:H12) -> 0
B2: System | E2: SOLUTION | M2: =SUM(I7:I12) -> 31
B3: The system that delivers value — software, configured products, hardware, data and services. A generalisation of Essence's Software System. | M3: =SUM(K7:K12) -> 0
B4: CURRENT STATE | C4: PROGRESS | D4: STATES ACHIEVED | E4: OWNER · AREA | M4: =SUM(J7:J12) -> 0
B5: =IF(M3=0,"Not started",INDEX(G7:G12,M3)) -> Not started | C5: =IF(M2=0,0,M1/M2) -> 0 | D5: =M4&" / "&6 -> 0 / 6 | E5: Kernel · Solution
B6: STATE | C6: ✔ | D6: CHECKLIST ITEM | E6: STATE STATUS
B7: 1. Architecture Selected | D7: The criteria for selecting the architecture are agreed. | E7: =COUNTIF(C7:C13,"✔")&" / 7" -> 0 / 7 | G7: Architecture Selected | H7: =COUNTIF(C7:C13,"✔") -> 0 | I7: 7 | J7: =IF(H7=I7,1,0) -> 0 | K7: =J7 -> 0
D8: The architecture's key concepts and properties are clearly defined. | G8: Demonstrable | H8: =COUNTIF(C14:C19,"✔") -> 0 | I8: 6 | J8: =IF(H8=I8,1,0) -> 0 | K8: =J8*K7 -> 0
D9: The selected architecture is clearly conceived. | G9: Usable | H9: =COUNTIF(C20:C26,"✔") -> 0 | I9: 7 | J9: =IF(H9=I9,1,0) -> 0 | K9: =J9*K8 -> 0
D10: The system boundary is known. | G10: Ready | H10: =COUNTIF(C27:C30,"✔") -> 0 | I10: 4 | J10: =IF(H10=I10,1,0) -> 0 | K10: =J10*K9 -> 0
D11: Significant decisions about the system's organization have been made. | G11: Operational | H11: =COUNTIF(C31:C33,"✔") -> 0 | I11: 3 | J11: =IF(H11=I11,1,0) -> 0 | K11: =J11*K10 -> 0
D12: Buy, build, and reuse decisions have been made. | G12: Retired | H12: =COUNTIF(C34:C37,"✔") -> 0 | I12: 4 | J12: =IF(H12=I12,1,0) -> 0 | K12: =J12*K11 -> 0
D13: The key technical risks are agreed.
B14: 2. Demonstrable | D14: The key architectural characteristics have been demonstrated. | E14: =COUNTIF(C14:C19,"✔")&" / 6" -> 0 / 6
D15: The system can be exercised and its performance measured.
D16: Critical configurations of the architecture have been demonstrated.
D17: Critical interfaces have been demonstrated.
D18: Integration with other existing systems has been demonstrated.
D19: Relevant stakeholders agree the demonstrated architecture is appropriate.
B20: 3. Usable | D20: The system can be operated by the stakeholders who use it. | E20: =COUNTIF(C20:C26,"✔")&" / 7" -> 0 / 7
D21: The functionality provided by the system has been tested.
D22: The system's performance is acceptable to the stakeholders.
D23: Defect levels are acceptable to the stakeholders.
D24: The system is sufficiently documented.
D25: The released system elements are known.
D26: The added value provided by the system is clear.
B27: 4. Ready | D27: Documentation on deploying and using the system in its intended environment is available. | E27: =COUNTIF(C27:C30,"✔")&" / 4" -> 0 / 4
D28: The stakeholder representatives accept the system as fit-for-purpose.
D29: The stakeholder representatives want to make the system available for use.
D30: Operational support is in place.
B31: 5. Operational | D31: The system has been made available to its intended stakeholders. | E31: =COUNTIF(C31:C33,"✔")&" / 3" -> 0 / 3
D32: At least one instance of the system is fully operational.
D33: The system is fully supported to the agreed service levels.
B34: 6. Retired | D34: The system has been replaced or discontinued. | E34: =COUNTIF(C34:C37,"✔")&" / 4" -> 0 / 4
D35: The system is no longer supported.
D36: There are no official stakeholders still using the system.
D37: Updates to the system will no longer be produced.

Sheet Work
B1: ← Dashboard | M1: =SUM(H7:H12) -> 11
B2: Work | E2: SOLUTION | M2: =SUM(I7:I12) -> 19
B3: The activity and effort applied to produce the result. | M3: =SUM(K7:K12) -> 2
B4: CURRENT STATE | C4: PROGRESS | D4: STATES ACHIEVED | E4: OWNER · AREA | M4: =SUM(J7:J12) -> 2
B5: =IF(M3=0,"Not started",INDEX(G7:G12,M3)) -> Prepared | C5: =IF(M2=0,0,M1/M2) -> 0.57894737 | D5: =M4&" / "&6 -> 2 / 6 | E5: Kernel · Endeavor
B6: STATE | C6: ✔ | D6: CHECKLIST ITEM | E6: STATE STATUS
B7: 1. Initiated | C7: ✔ | D7: The constraints and funding context are clear. | E7: =COUNTIF(C7:C10,"✔")&" / 4" -> 4 / 4 | G7: Initiated | H7: =COUNTIF(C7:C10,"✔") -> 4 | I7: 4 | J7: =IF(H7=I7,1,0) -> 1 | K7: =J7 -> 1
C8: ✔ | D8: The sponsors are identified. | G8: Prepared | H8: =COUNTIF(C11:C15,"✔") -> 5 | I8: 5 | J8: =IF(H8=I8,1,0) -> 1 | K8: =J8*K7 -> 1
C9: ✔ | D9: The priority is clear. | G9: Started | H9: =COUNTIF(C16:C18,"✔") -> 2 | I9: 3 | J9: =IF(H9=I9,1,0) -> 0 | K9: =J9*K8 -> 0
C10: ✔ | D10: The work has been requested. | G10: Under Control | H10: =COUNTIF(C19:C21,"✔") -> 0 | I10: 3 | J10: =IF(H10=I10,1,0) -> 0 | K10: =J10*K9 -> 0
B11: 2. Prepared | C11: ✔ | D11: A credible plan and estimate are in place. | E11: =COUNTIF(C11:C15,"✔")&" / 5" -> 5 / 5 | G11: Concluded | H11: =COUNTIF(C22:C23,"✔") -> 0 | I11: 2 | J11: =IF(H11=I11,1,0) -> 0 | K11: =J11*K10 -> 0
C12: ✔ | D12: Funding and resources are committed. | G12: Closed | H12: =COUNTIF(C24:C25,"✔") -> 0 | I12: 2 | J12: =IF(H12=I12,1,0) -> 0 | K12: =J12*K11 -> 0
C13: ✔ | D13: Key risks are identified and being addressed.
C14: ✔ | D14: The criteria for success are agreed.
C15: ✔ | D15: Governance and the way of working are in place.
B16: 3. Started | C16: ✔ | D16: The work has started and progress is being monitored. | E16: =COUNTIF(C16:C18,"✔")&" / 3" -> 2 / 3
C17: ✔ | D17: The team is performing the work.
D18: Tasks are being completed.
B19: 4. Under Control | D19: Tasks are being completed and risks are under control. | E19: =COUNTIF(C19:C21,"✔")&" / 3" -> 0 / 3
D20: Estimates are updated and re-work is under control.
D21: Measures of progress and velocity are available.
B22: 5. Concluded | D22: The work to produce the results has concluded. | E22: =COUNTIF(C22:C23,"✔")&" / 2" -> 0 / 2
D23: The results have been achieved and accepted by the stakeholders.
B24: 6. Closed | D24: Everything has been archived and lessons captured. | E24: =COUNTIF(C24:C25,"✔")&" / 2" -> 0 / 2
D25: The budget is reconciled and the team released.

Sheet Team
B1: ← Dashboard | M1: =SUM(H7:H11) -> 11
B2: Team | E2: SOLUTION | M2: =SUM(I7:I11) -> 17
B3: The group actively developing, maintaining and supporting the system. | M3: =SUM(K7:K11) -> 2
B4: CURRENT STATE | C4: PROGRESS | D4: STATES ACHIEVED | E4: OWNER · AREA | M4: =SUM(J7:J11) -> 2
B5: =IF(M3=0,"Not started",INDEX(G7:G11,M3)) -> Formed | C5: =IF(M2=0,0,M1/M2) -> 0.64705882 | D5: =M4&" / "&5 -> 2 / 5 | E5: Kernel · Endeavor
B6: STATE | C6: ✔ | D6: CHECKLIST ITEM | E6: STATE STATUS
B7: 1. Seeded | C7: ✔ | D7: The team mission is defined. | E7: =COUNTIF(C7:C11,"✔")&" / 5" -> 5 / 5 | G7: Seeded | H7: =COUNTIF(C7:C11,"✔") -> 5 | I7: 5 | J7: =IF(H7=I7,1,0) -> 1 | K7: =J7 -> 1
C8: ✔ | D8: The constraints on the team are known. | G8: Formed | H8: =COUNTIF(C12:C15,"✔") -> 4 | I8: 4 | J8: =IF(H8=I8,1,0) -> 1 | K8: =J8*K7 -> 1
C9: ✔ | D9: The required competencies are identified. | G9: Collaborating | H9: =COUNTIF(C16:C18,"✔") -> 2 | I9: 3 | J9: =IF(H9=I9,1,0) -> 0 | K9: =J9*K8 -> 0
C10: ✔ | D10: The leadership and governance model is selected. | G10: Performing | H10: =COUNTIF(C19:C21,"✔") -> 0 | I10: 3 | J10: =IF(H10=I10,1,0) -> 0 | K10: =J10*K9 -> 0
C11: ✔ | D11: The team size and composition are agreed. | G11: Adjourned | H11: =COUNTIF(C22:C23,"✔") -> 0 | I11: 2 | J11: =IF(H11=I11,1,0) -> 0 | K11: =J11*K10 -> 0
B12: 2. Formed | C12: ✔ | D12: Enough team members are recruited to start. | E12: =COUNTIF(C12:C15,"✔")&" / 4" -> 4 / 4
C13: ✔ | D13: The roles and responsibilities are understood.
C14: ✔ | D14: The members understand how to work together.
C15: ✔ | D15: The members are committed.
B16: 3. Collaborating | C16: ✔ | D16: The team works as one cohesive unit. | E16: =COUNTIF(C16:C18,"✔")&" / 3" -> 2 / 3
C17: ✔ | D17: Communication is open and honest.
D18: The team is focused on achieving the mission.
B19: 4. Performing | D19: The team consistently meets its commitments. | E19: =COUNTIF(C19:C21,"✔")&" / 3" -> 0 / 3
D20: The team adapts to the changing context.
D21: The team identifies and addresses problems without outside help.
B22: 5. Adjourned | D22: The team's responsibilities have been handed over or fulfilled. | E22: =COUNTIF(C22:C23,"✔")&" / 2" -> 0 / 2
D23: The resources have been released.

Sheet Way of Working
B1: ← Dashboard | M1: =SUM(H7:H12) -> 7
B2: Way of Working | E2: SOLUTION | M2: =SUM(I7:I12) -> 17
B3: The tailored set of practices and tools the team uses to guide its work. | M3: =SUM(K7:K12) -> 2
B4: CURRENT STATE | C4: PROGRESS | D4: STATES ACHIEVED | E4: OWNER · AREA | M4: =SUM(J7:J12) -> 2
B5: =IF(M3=0,"Not started",INDEX(G7:G12,M3)) -> Foundation Established | C5: =IF(M2=0,0,M1/M2) -> 0.41176471 | D5: =M4&" / "&6 -> 2 / 6 | E5: Kernel · Endeavor
B6: STATE | C6: ✔ | D6: CHECKLIST ITEM | E6: STATE STATUS
B7: 1. Principles Established | C7: ✔ | D7: The principles and constraints are committed to by the team. | E7: =COUNTIF(C7:C9,"✔")&" / 3" -> 3 / 3 | G7: Principles Established | H7: =COUNTIF(C7:C9,"✔") -> 3 | I7: 3 | J7: =IF(H7=I7,1,0) -> 1 | K7: =J7 -> 1
C8: ✔ | D8: The principles are agreed by the stakeholders. | G8: Foundation Established | H8: =COUNTIF(C10:C12,"✔") -> 3 | I8: 3 | J8: =IF(H8=I8,1,0) -> 1 | K8: =J8*K7 -> 1
C9: ✔ | D9: The tool and practice needs are understood. | G9: In Use | H9: =COUNTIF(C13:C15,"✔") -> 1 | I9: 3 | J9: =IF(H9=I9,1,0) -> 0 | K9: =J9*K8 -> 0
B10: 2. Foundation Established | C10: ✔ | D10: The key practices and tools are selected and integrated enough to start. | E10: =COUNTIF(C10:C12,"✔")&" / 3" -> 3 / 3 | G10: In Place | H10: =COUNTIF(C16:C18,"✔") -> 0 | I10: 3 | J10: =IF(H10=I10,1,0) -> 0 | K10: =J10*K9 -> 0
C11: ✔ | D11: The non-negotiable practices are agreed. | G11: Working Well | H11: =COUNTIF(C19:C21,"✔") -> 0 | I11: 3 | J11: =IF(H11=I11,1,0) -> 0 | K11: =J11*K10 -> 0
C12: ✔ | D12: The capability gaps are understood. | G12: Retired | H12: =COUNTIF(C22:C23,"✔") -> 0 | I12: 2 | J12: =IF(H12=I12,1,0) -> 0 | K12: =J12*K11 -> 0
B13: 3. In Use | C13: ✔ | D13: The practices and tools are in use by the team. | E13: =COUNTIF(C13:C15,"✔")&" / 3" -> 1 / 3
D14: The team is adapting the way of working to its needs.
D15: Feedback mechanisms are in place.
B16: 4. In Place | D16: The whole team is using the way of working. | E16: =COUNTIF(C16:C18,"✔")&" / 3" -> 0 / 3
D17: The team has access to the tools.
D18: The way of working is regularly inspected.
B19: 5. Working Well | D19: The team predictably delivers using the way of working. | E19: =COUNTIF(C19:C21,"✔")&" / 3" -> 0 / 3
D20: The practices are applied naturally and tuned continuously.
D21: The team continuously improves the way of working.
B22: 6. Retired | D22: The way of working is no longer in use. | E22: =COUNTIF(C22:C23,"✔")&" / 2" -> 0 / 2
D23: The lessons learned have been captured.

Sheet Architectural Drivers
B1: ← Dashboard | M1: =SUM(H7:H11) -> 7
B2: Architectural Drivers | E2: SOLUTION | M2: =SUM(I7:I11) -> 10
B3: The significant concerns, goals, constraints and quality attributes that shape the architecture. | M3: =SUM(K7:K11) -> 3
B4: CURRENT STATE | C4: PROGRESS | D4: STATES ACHIEVED | E4: OWNER · AREA | M4: =SUM(J7:J11) -> 3
B5: =IF(M3=0,"Not started",INDEX(G7:G11,M3)) -> Quantified | C5: =IF(M2=0,0,M1/M2) -> 0.7 | D5: =M4&" / "&5 -> 3 / 5 | E5: MVA · Solution
B6: STATE | C6: ✔ | D6: CHECKLIST ITEM | E6: STATE STATUS
B7: 1. Identified | C7: ✔ | D7: The architecturally-significant concerns and their owners are surfaced. | E7: =COUNTIF(C7:C8,"✔")&" / 2" -> 2 / 2 | G7: Identified | H7: =COUNTIF(C7:C8,"✔") -> 2 | I7: 2 | J7: =IF(H7=I7,1,0) -> 1 | K7: =J7 -> 1
C8: ✔ | D8: A candidate list of drivers exists. | G8: Prioritised | H8: =COUNTIF(C9:C10,"✔") -> 2 | I8: 2 | J8: =IF(H8=I8,1,0) -> 1 | K8: =J8*K7 -> 1
B9: 2. Prioritised | C9: ✔ | D9: The significant few drivers are agreed and ranked. | E9: =COUNTIF(C9:C10,"✔")&" / 2" -> 2 / 2 | G9: Quantified | H9: =COUNTIF(C11:C12,"✔") -> 2 | I9: 2 | J9: =IF(H9=I9,1,0) -> 1 | K9: =J9*K8 -> 1
C10: ✔ | D10: The trivial many are explicitly deferred. | G10: Addressed | H10: =COUNTIF(C13:C14,"✔") -> 1 | I10: 2 | J10: =IF(H10=I10,1,0) -> 0 | K10: =J10*K9 -> 0
B11: 3. Quantified | C11: ✔ | D11: Each significant driver has a measurable success criterion. | E11: =COUNTIF(C11:C12,"✔")&" / 2" -> 2 / 2 | G11: Sustained | H11: =COUNTIF(C15:C16,"✔") -> 0 | I11: 2 | J11: =IF(H11=I11,1,0) -> 0 | K11: =J11*K10 -> 0
C12: ✔ | D12: The criteria are agreed with the stakeholders.
B13: 4. Addressed | C13: ✔ | D13: The drivers are reflected in the decisions and the architecture. | E13: =COUNTIF(C13:C14,"✔")&" / 2" -> 1 / 2
D14: Evidence shows the drivers are being met.
B15: 5. Sustained | D15: The drivers are monitored as the context changes. | E15: =COUNTIF(C15:C16,"✔")&" / 2" -> 0 / 2
D16: The drivers are re-validated and updated when needed.

Sheet Architecture
B1: ← Dashboard | M1: =SUM(H7:H12) -> 7
B2: Architecture | E2: SOLUTION | M2: =SUM(I7:I12) -> 11
B3: The minimum set of structures, building blocks and views needed to satisfy the significant drivers and enable delivery. | M3: =SUM(K7:K12) -> 3
B4: CURRENT STATE | C4: PROGRESS | D4: STATES ACHIEVED | E4: OWNER · AREA | M4: =SUM(J7:J12) -> 3
B5: =IF(M3=0,"Not started",INDEX(G7:G12,M3)) -> Demonstrated | C5: =IF(M2=0,0,M1/M2) -> 0.63636364 | D5: =M4&" / "&6 -> 3 / 6 | E5: MVA · Solution
B6: STATE | C6: ✔ | D6: CHECKLIST ITEM | E6: STATE STATUS
B7: 1. Envisioned | C7: ✔ | D7: The target direction, scope and value are agreed on a page. | E7: =COUNTIF(C7:C8,"✔")&" / 2" -> 2 / 2 | G7: Envisioned | H7: =COUNTIF(C7:C8,"✔") -> 2 | I7: 2 | J7: =IF(H7=I7,1,0) -> 1 | K7: =J7 -> 1
C8: ✔ | D8: The key stakeholders share the vision. | G8: Outlined | H8: =COUNTIF(C9:C10,"✔") -> 2 | I8: 2 | J8: =IF(H8=I8,1,0) -> 1 | K8: =J8*K7 -> 1
B9: 2. Outlined | C9: ✔ | D9: The minimum viable structure, boundaries and interfaces are defined. | E9: =COUNTIF(C9:C10,"✔")&" / 2" -> 2 / 2 | G9: Demonstrated | H9: =COUNTIF(C11:C12,"✔") -> 2 | I9: 2 | J9: =IF(H9=I9,1,0) -> 1 | K9: =J9*K8 -> 1
C10: ✔ | D10: Only the building blocks needed now are included. | G10: Usable | H10: =COUNTIF(C13:C14,"✔") -> 1 | I10: 2 | J10: =IF(H10=I10,1,0) -> 0 | K10: =J10*K9 -> 0
B11: 3. Demonstrated | C11: ✔ | D11: The riskiest parts are proven via spike, reference or increment. | E11: =COUNTIF(C11:C12,"✔")&" / 2" -> 2 / 2 | G11: Established | H11: =COUNTIF(C15:C15,"✔") -> 0 | I11: 1 | J11: =IF(H11=I11,1,0) -> 0 | K11: =J11*K10 -> 0
C12: ✔ | D12: The key decisions are validated by evidence. | G12: Evolving | H12: =COUNTIF(C16:C17,"✔") -> 0 | I12: 2 | J12: =IF(H12=I12,1,0) -> 0 | K12: =J12*K11 -> 0
B13: 4. Usable | C13: ✔ | D13: The architecture is actively guiding and constraining delivery. | E13: =COUNTIF(C13:C14,"✔")&" / 2" -> 1 / 2
D14: The teams are building within it.
B15: 5. Established | D15: The architecture is in operation and delivering the intended outcomes. | E15: =COUNTIF(C15:C15,"✔")&" / 1" -> 0 / 1
B16: 6. Evolving | D16: The architecture is changing under managed, continuous adaptation. | E16: =COUNTIF(C16:C17,"✔")&" / 2" -> 0 / 2
D17: Change is handled without big-bang rework.

Sheet Architecture Decisions
B1: ← Dashboard | M1: =SUM(H7:H11) -> 4
B2: Architecture Decisions | E2: SOLUTION | M2: =SUM(I7:I11) -> 5
B3: The significant, costly-to-reverse choices that are the architecture. | M3: =SUM(K7:K11) -> 4
B4: CURRENT STATE | C4: PROGRESS | D4: STATES ACHIEVED | E4: OWNER · AREA | M4: =SUM(J7:J11) -> 4
B5: =IF(M3=0,"Not started",INDEX(G7:G11,M3)) -> Communicated | C5: =IF(M2=0,0,M1/M2) -> 0.8 | D5: =M4&" / "&5 -> 4 / 5 | E5: MVA · Solution
B6: STATE | C6: ✔ | D6: CHECKLIST ITEM | E6: STATE STATUS
B7: 1. Needed | C7: ✔ | D7: A significant, costly-to-reverse decision point is recognised and owned. | E7: =COUNTIF(C7:C7,"✔")&" / 1" -> 1 / 1 | G7: Needed | H7: =COUNTIF(C7:C7,"✔") -> 1 | I7: 1 | J7: =IF(H7=I7,1,0) -> 1 | K7: =J7 -> 1
B8: 2. Framed | C8: ✔ | D8: The options, trade-offs and the last responsible moment are understood. | E8: =COUNTIF(C8:C8,"✔")&" / 1" -> 1 / 1 | G8: Framed | H8: =COUNTIF(C8:C8,"✔") -> 1 | I8: 1 | J8: =IF(H8=I8,1,0) -> 1 | K8: =J8*K7 -> 1
B9: 3. Decided | C9: ✔ | D9: The choice is made and recorded with rationale and consequences (ADR). | E9: =COUNTIF(C9:C9,"✔")&" / 1" -> 1 / 1 | G9: Decided | H9: =COUNTIF(C9:C9,"✔") -> 1 | I9: 1 | J9: =IF(H9=I9,1,0) -> 1 | K9: =J9*K8 -> 1
B10: 4. Communicated | C10: ✔ | D10: The decision is known and accepted by those it affects. | E10: =COUNTIF(C10:C10,"✔")&" / 1" -> 1 / 1 | G10: Communicated | H10: =COUNTIF(C10:C10,"✔") -> 1 | I10: 1 | J10: =IF(H10=I10,1,0) -> 1 | K10: =J10*K9 -> 1
B11: 5. Validated | D11: The decision is proven by evidence and outcome, or revisited. | E11: =COUNTIF(C11:C11,"✔")&" / 1" -> 0 / 1 | G11: Validated | H11: =COUNTIF(C11:C11,"✔") -> 0 | I11: 1 | J11: =IF(H11=I11,1,0) -> 0 | K11: =J11*K10 -> 0

Sheet Paved Road
B1: ← Dashboard | M1: =SUM(H7:H11) -> 5
B2: Paved Road | E2: ENTERPRISE | M2: =SUM(I7:I11) -> 10
B3: The reusable service chassis of approved products, patterns and standards that makes the compliant choice the easy one. | M3: =SUM(K7:K11) -> 2
B4: CURRENT STATE | C4: PROGRESS | D4: STATES ACHIEVED | E4: OWNER · AREA | M4: =SUM(J7:J11) -> 2
B5: =IF(M3=0,"Not started",INDEX(G7:G11,M3)) -> Established | C5: =IF(M2=0,0,M1/M2) -> 0.5 | D5: =M4&" / "&5 -> 2 / 5 | E5: MVA · Solution
B6: STATE | C6: ✔ | D6: CHECKLIST ITEM | E6: STATE STATUS
B7: 1. Seeded | C7: ✔ | D7: The need for a paved road is recognised. | E7: =COUNTIF(C7:C8,"✔")&" / 2" -> 2 / 2 | G7: Seeded | H7: =COUNTIF(C7:C8,"✔") -> 2 | I7: 2 | J7: =IF(H7=I7,1,0) -> 1 | K7: =J7 -> 1
C8: ✔ | D8: A first approved default or two exists. | G8: Established | H8: =COUNTIF(C9:C10,"✔") -> 2 | I8: 2 | J8: =IF(H8=I8,1,0) -> 1 | K8: =J8*K7 -> 1
B9: 2. Established | C9: ✔ | D9: A coherent service chassis of approved products, patterns and standards is published. | E9: =COUNTIF(C9:C10,"✔")&" / 2" -> 2 / 2 | G9: Adopted | H9: =COUNTIF(C11:C12,"✔") -> 1 | I9: 2 | J9: =IF(H9=I9,1,0) -> 0 | K9: =J9*K8 -> 0
C10: ✔ | D10: The paved road is self-serviceable. | G10: Pervasive | H10: =COUNTIF(C13:C14,"✔") -> 0 | I10: 2 | J10: =IF(H10=I10,1,0) -> 0 | K10: =J10*K9 -> 0
B11: 3. Adopted | C11: ✔ | D11: Teams build on the paved road by default. | E11: =COUNTIF(C11:C12,"✔")&" / 2" -> 1 / 2 | G11: Evolving | H11: =COUNTIF(C15:C16,"✔") -> 0 | I11: 2 | J11: =IF(H11=I11,1,0) -> 0 | K11: =J11*K10 -> 0
D12: On-road choices need no review.
B13: 4. Pervasive | D13: The paved road is the norm across the estate. | E13: =COUNTIF(C13:C14,"✔")&" / 2" -> 0 / 2
D14: Going off-road is the rare, justified exception.
B15: 5. Evolving | D15: The paved road is continuously widened and pruned. | E15: =COUNTIF(C15:C16,"✔")&" / 2" -> 0 / 2
D16: Learnings from reviews feed back into it.

Sheet Governance
B1: ← Dashboard | M1: =SUM(H7:H11) -> 7
B2: Governance | E2: SPANS LEVELS | M2: =SUM(I7:I11) -> 10
B3: The lightweight decision rights, guardrails and assurance that keep delivery aligned with intent. | M3: =SUM(K7:K11) -> 3
B4: CURRENT STATE | C4: PROGRESS | D4: STATES ACHIEVED | E4: OWNER · AREA | M4: =SUM(J7:J11) -> 3
B5: =IF(M3=0,"Not started",INDEX(G7:G11,M3)) -> Guiding | C5: =IF(M2=0,0,M1/M2) -> 0.7 | D5: =M4&" / "&5 -> 3 / 5 | E5: MVG · Endeavor
B6: STATE | C6: ✔ | D6: CHECKLIST ITEM | E6: STATE STATUS
B7: 1. Initiated | C7: ✔ | D7: The decision rights and minimal guardrails are agreed. | E7: =COUNTIF(C7:C8,"✔")&" / 2" -> 2 / 2 | G7: Initiated | H7: =COUNTIF(C7:C8,"✔") -> 2 | I7: 2 | J7: =IF(H7=I7,1,0) -> 1 | K7: =J7 -> 1
C8: ✔ | D8: It is clear who decides what. | G8: Engaged | H8: =COUNTIF(C9:C10,"✔") -> 2 | I8: 2 | J8: =IF(H8=I8,1,0) -> 1 | K8: =J8*K7 -> 1
B9: 2. Engaged | C9: ✔ | D9: A lean governance cadence operates. | E9: =COUNTIF(C9:C10,"✔")&" / 2" -> 2 / 2 | G9: Guiding | H9: =COUNTIF(C11:C12,"✔") -> 2 | I9: 2 | J9: =IF(H9=I9,1,0) -> 1 | K9: =J9*K8 -> 1
C10: ✔ | D10: The teams know the guardrails. | G10: Assured | H10: =COUNTIF(C13:C14,"✔") -> 1 | I10: 2 | J10: =IF(H10=I10,1,0) -> 0 | K10: =J10*K9 -> 0
B11: 3. Guiding | C11: ✔ | D11: Decisions flow within the guardrails. | E11: =COUNTIF(C11:C12,"✔")&" / 2" -> 2 / 2 | G11: Effective | H11: =COUNTIF(C15:C16,"✔") -> 0 | I11: 2 | J11: =IF(H11=I11,1,0) -> 0 | K11: =J11*K10 -> 0
C12: ✔ | D12: Only exceptions are escalated.
B13: 4. Assured | C13: ✔ | D13: Conformance is evidenced where it genuinely matters. | E13: =COUNTIF(C13:C14,"✔")&" / 2" -> 1 / 2
D14: The architecture reviews are acted upon.
B15: 5. Effective | D15: Governance demonstrably enables delivery. | E15: =COUNTIF(C15:C16,"✔")&" / 2" -> 0 / 2
D16: The governance itself is continuously tuned and lightened.

Sheet Business Scenario
B1: ← Dashboard | M1: =SUM(H7:H10) -> 8
B2: Business Scenario | E2: ENTERPRISE | M2: =SUM(I7:I10) -> 8
B3: The structured understanding of the business need, progressing through the method's phases until it can drive the architecture. | M3: =SUM(K7:K10) -> 4
B4: CURRENT STATE | C4: PROGRESS | D4: STATES ACHIEVED | E4: OWNER · AREA | M4: =SUM(J7:J10) -> 4
B5: =IF(M3=0,"Not started",INDEX(G7:G10,M3)) -> Released | C5: =IF(M2=0,0,M1/M2) -> 1 | D5: =M4&" / "&4 -> 4 / 4 | E5: Business Scenarios · Customer
B6: STATE | C6: ✔ | D6: CHECKLIST ITEM | E6: STATE STATUS
B7: 1. Premise Formed | C7: ✔ | D7: The business premise — problem, environment and objectives — is captured. | E7: =COUNTIF(C7:C8,"✔")&" / 2" -> 2 / 2 | G7: Premise Formed | H7: =COUNTIF(C7:C8,"✔") -> 2 | I7: 2 | J7: =IF(H7=I7,1,0) -> 1 | K7: =J7 -> 1
C8: ✔ | D8: The customer and their goal are clear. | G8: Verified | H8: =COUNTIF(C9:C10,"✔") -> 2 | I8: 2 | J8: =IF(H8=I8,1,0) -> 1 | K8: =J8*K7 -> 1
B9: 2. Verified | C9: ✔ | D9: The five elements (problem, environment, outcomes, human and system actors) are gathered. | E9: =COUNTIF(C9:C10,"✔")&" / 2" -> 2 / 2 | G9: Refined | H9: =COUNTIF(C11:C12,"✔") -> 2 | I9: 2 | J9: =IF(H9=I9,1,0) -> 1 | K9: =J9*K8 -> 1
C10: ✔ | D10: An initial model is verified with the stakeholders. | G10: Released | H10: =COUNTIF(C13:C14,"✔") -> 2 | I10: 2 | J10: =IF(H10=I10,1,0) -> 1 | K10: =J10*K9 -> 1
B11: 3. Refined | C11: ✔ | D11: The objectives are made SMART. | E11: =COUNTIF(C11:C12,"✔")&" / 2" -> 2 / 2
C12: ✔ | D12: The scenario is refined to fit-for-purpose with the stakeholders.
B13: 4. Released | C13: ✔ | D13: The Business Scenario is documented and signed off. | E13: =COUNTIF(C13:C14,"✔")&" / 2" -> 2 / 2
C14: ✔ | D14: It is ready to drive the architecture.

Sheet Service Blueprint
B1: ← Dashboard | M1: =SUM(H7:H11) -> 7
B2: Service Blueprint | E2: SOLUTION | M2: =SUM(I7:I11) -> 10
B3: A map of one service journey across all its layers, sliced and progressed like a use case. | M3: =SUM(K7:K11) -> 3
B4: CURRENT STATE | C4: PROGRESS | D4: STATES ACHIEVED | E4: OWNER · AREA | M4: =SUM(J7:J11) -> 3
B5: =IF(M3=0,"Not started",INDEX(G7:G11,M3)) -> Blueprinted | C5: =IF(M2=0,0,M1/M2) -> 0.7 | D5: =M4&" / "&5 -> 3 / 5 | E5: Service Blueprint · Customer
B6: STATE | C6: ✔ | D6: CHECKLIST ITEM | E6: STATE STATUS
B7: 1. Scoped | C7: ✔ | D7: The service journey and customer to blueprint are chosen and bounded. | E7: =COUNTIF(C7:C8,"✔")&" / 2" -> 2 / 2 | G7: Scoped | H7: =COUNTIF(C7:C8,"✔") -> 2 | I7: 2 | J7: =IF(H7=I7,1,0) -> 1 | K7: =J7 -> 1
C8: ✔ | D8: The customer and their goal are clear. | G8: Frontstage Mapped | H8: =COUNTIF(C9:C10,"✔") -> 2 | I8: 2 | J8: =IF(H8=I8,1,0) -> 1 | K8: =J8*K7 -> 1
B9: 2. Frontstage Mapped | C9: ✔ | D9: The customer-actions row and frontstage touchpoints are laid out across the line of interaction. | E9: =COUNTIF(C9:C10,"✔")&" / 2" -> 2 / 2 | G9: Blueprinted | H9: =COUNTIF(C11:C12,"✔") -> 2 | I9: 2 | J9: =IF(H9=I9,1,0) -> 1 | K9: =J9*K8 -> 1
C10: ✔ | D10: The physical evidence is captured. | G10: Validated | H10: =COUNTIF(C13:C14,"✔") -> 1 | I10: 2 | J10: =IF(H10=I10,1,0) -> 0 | K10: =J10*K9 -> 0
B11: 3. Blueprinted | C11: ✔ | D11: Backstage actions and support processes / systems are added below the lines of visibility and internal interaction. | E11: =COUNTIF(C11:C12,"✔")&" / 2" -> 2 / 2 | G11: In Operation | H11: =COUNTIF(C15:C16,"✔") -> 0 | I11: 2 | J11: =IF(H11=I11,1,0) -> 0 | K11: =J11*K10 -> 0
C12: ✔ | D12: The blueprint is complete across all three lines.
B13: 4. Validated | C13: ✔ | D13: The blueprint is walked through with customers and staff. | E13: =COUNTIF(C13:C14,"✔")&" / 2" -> 1 / 2
D14: Fail points, waits and hand-offs are surfaced and agreed.
B15: 5. In Operation | D15: The service is delivered to the blueprint. | E15: =COUNTIF(C15:C16,"✔")&" / 2" -> 0 / 2
D16: The blueprint is kept live as the service evolves.
